README.md
setup.py
libhttpdna/__init__.py
libhttpdna/libhttpdna.py
libhttpdna.egg-info/PKG-INFO
libhttpdna.egg-info/SOURCES.txt
libhttpdna.egg-info/dependency_links.txt
libhttpdna.egg-info/top_level.txt