Metadata-Version: 1.1
Name: libhttpdna
Version: 0.1.0
Summary: A library for working with DNA.
Home-page: https://github.com/antonybholmes/libhttpdna
Author: Antony B Holmes
Author-email: antony.b.holmes@gmail.com
License: UNKNOWN
Platform: UNKNOWN
Classifier: Programming Language :: Python :: 3
Classifier: License :: OSI Approved :: MIT License
Classifier: Operating System :: OS Independent
